ONAP/__init__.py
ONAP/classes/__init__.py
ONAP/classes/directed_graph.py
ONAP/classes/graph.py
ONAP/functions/__init__.py
ONAP/functions/community/__init__.py
ONAP/functions/community/modularity.py
ONAP/functions/community/modularity_max_detection.py
ONAP/functions/components/__init__.py
ONAP/functions/components/biconnected.py
ONAP/functions/components/connected.py
ONAP/functions/graph_embedding/__init__.py
ONAP/functions/graph_embedding/node2vec.py
ONAP/functions/graph_embedding/node2vec/__init__.py
ONAP/functions/graph_embedding/node2vec/edges.py
ONAP/functions/graph_embedding/node2vec/node2vec.py
ONAP/functions/graph_embedding/node2vec/parallel.py
ONAP/functions/not_sorted/__init__.py
ONAP/functions/not_sorted/pagerank.py
ONAP/functions/structural_holes/AP_Greedy.py
ONAP/functions/structural_holes/HAM.py
ONAP/functions/structural_holes/HIS.py
ONAP/functions/structural_holes/MaxD.py
ONAP/functions/structural_holes/__init__.py
ONAP/tests/__init__.py
ONAP/tests/test_1.py
ONAP/tests/test_2.py
ONAP/tests/utils.py
ONAP/utils/__init__.py
ONAP/utils/convert_to_matrix.py
ONAP/utils/decorators.py
ONAP/utils/mapped_queue.py
ONAP-0.0.4.dist-info/LICENSE
ONAP-0.0.4.dist-info/METADATA
ONAP-0.0.4.dist-info/WHEEL
ONAP-0.0.4.dist-info/top_level.txt
ONAP-0.0.4.dist-info/RECORD
