Metadata-Version: 2.1
Name: ONAP
Version: 0.0.4
Summary: ONAP testing
Home-page: https://github.com/willingnesshxl/OpenGraph
Author: A, B, C, D
Author-email: ONAP@163.com
License: MIT
Keywords: ONAP
Platform: UNKNOWN
Requires-Python: >=3
Requires-Dist: gensim (==3.8.1)
